celespy/__init__.py
celespy/astro/__init__.py
celespy/astro/astrofunc.py
celespy/astro/astrosource.py
celespy/astro/other/gaia_medium.fits
celespy/image/__init__.py
celespy/image/data.py
celespy/image/image.py
celespy-0.0.5.dist-info/METADATA
celespy-0.0.5.dist-info/WHEEL
celespy-0.0.5.dist-info/top_level.txt
celespy-0.0.5.dist-info/RECORD
